toad/__init__.py
toad/__main__.py
toad/_loop.py
toad/about.py
toad/agent.py
toad/agent_schema.py
toad/agents.py
toad/answer.py
toad/app.py
toad/atomic.py
toad/cli.py
toad/code_analyze.py
toad/complete.py
toad/constants.py
toad/conversation_markdown.py
toad/danger.py
toad/db.py
toad/dec.py
toad/directory.py
toad/directory_watcher.py
toad/fuzzy.py
toad/gist.py
toad/history.py
toad/jsonrpc.py
toad/menus.py
toad/messages.py
toad/option_content.py
toad/os.py
toad/path_complete.py
toad/path_filter.py
toad/paths.py
toad/pill.py
toad/protocol.py
toad/settings.py
toad/settings_schema.py
toad/shell.py
toad/shell_read.py
toad/slash_command.py
toad/toad.tcss
toad/version.py
toad/acp/agent.py
toad/acp/api.py
toad/acp/encode_tool_call_id.py
toad/acp/messages.py
toad/acp/prompt.py
toad/acp/protocol.py
toad/ansi/__init__.py
toad/ansi/_ansi.py
toad/ansi/_ansi_colors.py
toad/ansi/_control_codes.py
toad/ansi/_keys.py
toad/ansi/_sgr_styles.py
toad/ansi/_stream_parser.py
toad/data/agents/ampcode.com.toml
toad/data/agents/augmentcode.com.toml
toad/data/agents/claude.com.toml
toad/data/agents/copilot.github.com.toml
toad/data/agents/docker.com.toml
toad/data/agents/geminicli.com.toml
toad/data/agents/goose.ai.toml
toad/data/agents/inference.huggingface.co.toml
toad/data/agents/kimi.com.toml
toad/data/agents/openai.com.toml
toad/data/agents/opencode.ai.toml
toad/data/agents/openhands.dev.toml
toad/data/agents/stakpak.dev.toml
toad/data/agents/vibe.mistral.ai.toml
toad/data/agents/vtcode.dev.toml
toad/data/images/frog.png
toad/data/sounds/question.wav
toad/data/sounds/turn-over.wav
toad/prompt/extract.py
toad/prompt/resource.py
toad/screens/action_modal.py
toad/screens/agent_modal.py
toad/screens/command_edit_modal.py
toad/screens/main.py
toad/screens/permissions.py
toad/screens/permissions.tcss
toad/screens/session_resume_modal.py
toad/screens/session_resume_modal.tcss
toad/screens/settings.py
toad/screens/settings.tcss
toad/screens/store.py
toad/screens/store.tcss
toad/visuals/columns.py
batrachian_toad-0.5.36.dist-info/METADATA
batrachian_toad-0.5.36.dist-info/WHEEL
batrachian_toad-0.5.36.dist-info/entry_points.txt
batrachian_toad-0.5.36.dist-info/licenses/LICENSE
batrachian_toad-0.5.36.dist-info/RECORD
