Metadata-Version: 2.4
Name: batrachian-toad
Version: 0.5.36
Summary: A unified experience for AI in your terminal.
License-File: LICENSE
Requires-Python: >=3.14
Requires-Dist: aiosqlite>=0.22.1
Requires-Dist: bashlex>=0.18
Requires-Dist: click>=8.2.1
Requires-Dist: gitpython>=3.1.44
Requires-Dist: google-re2>=1.1.20251105
Requires-Dist: httpx>=0.28.1
Requires-Dist: notify-py>=0.3.43
Requires-Dist: packaging>=25.0
Requires-Dist: pathspec>=0.12.1
Requires-Dist: platformdirs>=4.3.8
Requires-Dist: psutil>=7.2.1
Requires-Dist: pyperclip>=1.11.0
Requires-Dist: rich
Requires-Dist: setproctitle>=1.3.7
Requires-Dist: textual-serve>=1.1.2
Requires-Dist: textual-speedups==0.2.1
Requires-Dist: textual[syntax]>=7.5.0
Requires-Dist: tree-sitter>=0.24.0
Requires-Dist: typeguard>=4.4.4
Requires-Dist: watchdog>=6.0.0
Requires-Dist: xdg-base-dirs>=6.0.2
